<annotation>
	<folder>frames</folder>
	<filename>vid14_img0166.jpg</filename>
	<path>C:\Users\danie\Google Drive\Pesquisa\Artigo Imagens\videos\frames\vid14_img0166.jpg</path>
	<source>
		<database>Unknown</database>
	</source>
	<size>
		<width>1280</width>
		<height>720</height>
		<depth>3</depth>
	</size>
	<segmented>0</segmented>
	<object>
		<name>pollen</name>
		<pose>Unspecified</pose>
		<truncated>0</truncated>
		<difficult>0</difficult>
		<bndbox>
			<xmin>156</xmin>
			<ymin>464</ymin>
			<xmax>291</xmax>
			<ymax>628</ymax>
		</bndbox>
	</object>
	<object>
		<name>pollen</name>
		<pose>Unspecified</pose>
		<truncated>0</truncated>
		<difficult>0</difficult>
		<bndbox>
			<xmin>436</xmin>
			<ymin>334</ymin>
			<xmax>615</xmax>
			<ymax>529</ymax>
		</bndbox>
	</object>
	<object>
		<name>pollen</name>
		<pose>Unspecified</pose>
		<truncated>0</truncated>
		<difficult>0</difficult>
		<bndbox>
			<xmin>685</xmin>
			<ymin>518</ymin>
			<xmax>824</xmax>
			<ymax>621</ymax>
		</bndbox>
	</object>
	<object>
		<name>pollen</name>
		<pose>Unspecified</pose>
		<truncated>1</truncated>
		<difficult>0</difficult>
		<bndbox>
			<xmin>735</xmin>
			<ymin>601</ymin>
			<xmax>887</xmax>
			<ymax>720</ymax>
		</bndbox>
	</object>
</annotation>
